easylink/__about__.py
easylink/__init__.py
easylink/_version.py
easylink/cli.py
easylink/configuration.py
easylink/graph_components.py
easylink/implementation.py
easylink/implementation_metadata.yaml
easylink/pipeline.py
easylink/pipeline_graph.py
easylink/pipeline_schema.py
easylink/rule.py
easylink/runner.py
easylink/step.py
easylink/devtools/implementation_creator.py
easylink/pipeline_schema_constants/__init__.py
easylink/pipeline_schema_constants/development.py
easylink/pipeline_schema_constants/main.py
easylink/pipeline_schema_constants/testing.py
easylink/steps/cascading/accept_all_pairs.def
easylink/steps/cascading/accept_all_pairs.py
easylink/steps/cascading/exclude_clustered.def
easylink/steps/cascading/exclude_clustered.py
easylink/steps/cascading/exclude_none.def
easylink/steps/cascading/exclude_none.py
easylink/steps/cascading/one_to_many_links_to_clusters.def
easylink/steps/cascading/one_to_many_links_to_clusters.py
easylink/steps/cascading/update_clusters_by_connected_components.def
easylink/steps/cascading/update_clusters_by_connected_components.py
easylink/steps/default/default_clusters_to_links.def
easylink/steps/default/default_clusters_to_links.py
easylink/steps/default/default_determining_exclusions.def
easylink/steps/default/default_determining_exclusions.py
easylink/steps/default/default_removing_records.def
easylink/steps/default/default_removing_records.py
easylink/steps/default/default_schema_alignment.def
easylink/steps/default/default_schema_alignment.py
easylink/steps/default/default_updating_clusters.def
easylink/steps/default/default_updating_clusters.py
easylink/steps/dev/README.md
easylink/steps/dev/build-containers-local.sh
easylink/steps/dev/build-containers-remote.sh
easylink/steps/dev/test.py
easylink/steps/dev/input_data/create_input_files.ipynb
easylink/steps/dev/input_data/input_file_1.csv
easylink/steps/dev/input_data/input_file_1.parquet
easylink/steps/dev/input_data/input_file_2.csv
easylink-0.2.7.dist-info/licenses/LICENSE
easylink-0.2.7.dist-info/METADATA
easylink-0.2.7.dist-info/WHEEL
easylink-0.2.7.dist-info/entry_points.txt
easylink-0.2.7.dist-info/top_level.txt
easylink-0.2.7.dist-info/RECORD
