Metadata-Version: 2.4
Name: easylink
Version: 0.2.7
Summary: A tool that allows users to build and run highly configurable record linkage/entity resolution pipelines.
Home-page: https://github.com/ihmeuw/easylink
Author: The EasyLink developers
Author-email: vivarium.dev@gmail.com
License: BSD-3-Clause
License-File: LICENSE
Requires-Dist: vivarium_build_utils<3.0.0,>=2.0.2
Requires-Dist: click
Requires-Dist: docker
Requires-Dist: graphviz
Requires-Dist: loguru
Requires-Dist: layered_config_tree>=3.0.0
Requires-Dist: networkx
Requires-Dist: pandas
Requires-Dist: pyyaml
Requires-Dist: pyarrow
Requires-Dist: requests
Requires-Dist: snakemake>=8.0.0
Requires-Dist: tqdm
Requires-Dist: snakemake-interface-executor-plugins<9.0.0
Requires-Dist: snakemake-executor-plugin-slurm
Requires-Dist: pandas-stubs
Requires-Dist: pyarrow-stubs
Requires-Dist: types-PyYAML
Provides-Extra: docs
Requires-Dist: sphinx<8.2.0; extra == "docs"
Requires-Dist: sphinx-rtd-theme; extra == "docs"
Requires-Dist: sphinx-autodoc-typehints; extra == "docs"
Requires-Dist: sphinx-click; extra == "docs"
Requires-Dist: sphinx-autobuild; extra == "docs"
Requires-Dist: typing_extensions; extra == "docs"
Provides-Extra: test
Requires-Dist: pytest; extra == "test"
Requires-Dist: pytest-cov; extra == "test"
Requires-Dist: pytest-mock; extra == "test"
Provides-Extra: dev
Requires-Dist: sphinx<8.2.0; extra == "dev"
Requires-Dist: sphinx-rtd-theme; extra == "dev"
Requires-Dist: sphinx-autodoc-typehints; extra == "dev"
Requires-Dist: sphinx-click; extra == "dev"
Requires-Dist: sphinx-autobuild; extra == "dev"
Requires-Dist: typing_extensions; extra == "dev"
Requires-Dist: pytest; extra == "dev"
Requires-Dist: pytest-cov; extra == "dev"
Requires-Dist: pytest-mock; extra == "dev"
Requires-Dist: black==22.3.0; extra == "dev"
Requires-Dist: isort; extra == "dev"
Requires-Dist: mypy; extra == "dev"
Dynamic: author
Dynamic: author-email
Dynamic: description
Dynamic: description-content-type
Dynamic: home-page
Dynamic: license
Dynamic: license-file
Dynamic: provides-extra
Dynamic: requires-dist
Dynamic: summary
